autogen/__init__.py
autogen/_pydantic.py
autogen/browser_utils.py
autogen/code_utils.py
autogen/exception_utils.py
autogen/formatting_utils.py
autogen/function_utils.py
autogen/graph_utils.py
autogen/math_utils.py
autogen/retrieve_utils.py
autogen/runtime_logging.py
autogen/token_count_utils.py
autogen/types.py
autogen/version.py
autogen/agentchat/__init__.py
autogen/agentchat/agent.py
autogen/agentchat/assistant_agent.py
autogen/agentchat/chat.py
autogen/agentchat/conversable_agent.py
autogen/agentchat/groupchat.py
autogen/agentchat/user_proxy_agent.py
autogen/agentchat/utils.py
autogen/agentchat/contrib/__init__.py
autogen/agentchat/contrib/agent_builder.py
autogen/agentchat/contrib/agent_optimizer.py
autogen/agentchat/contrib/captainagent.py
autogen/agentchat/contrib/gpt_assistant_agent.py
autogen/agentchat/contrib/img_utils.py
autogen/agentchat/contrib/llamaindex_conversable_agent.py
autogen/agentchat/contrib/llava_agent.py
autogen/agentchat/contrib/math_user_proxy_agent.py
autogen/agentchat/contrib/multimodal_conversable_agent.py
autogen/agentchat/contrib/qdrant_retrieve_user_proxy_agent.py
autogen/agentchat/contrib/reasoning_agent.py
autogen/agentchat/contrib/retrieve_assistant_agent.py
autogen/agentchat/contrib/retrieve_user_proxy_agent.py
autogen/agentchat/contrib/society_of_mind_agent.py
autogen/agentchat/contrib/swarm_agent.py
autogen/agentchat/contrib/text_analyzer_agent.py
autogen/agentchat/contrib/tool_retriever.py
autogen/agentchat/contrib/web_surfer.py
autogen/agentchat/contrib/agent_eval/agent_eval.py
autogen/agentchat/contrib/agent_eval/criterion.py
autogen/agentchat/contrib/agent_eval/critic_agent.py
autogen/agentchat/contrib/agent_eval/quantifier_agent.py
autogen/agentchat/contrib/agent_eval/subcritic_agent.py
autogen/agentchat/contrib/agent_eval/task.py
autogen/agentchat/contrib/capabilities/__init__.py
autogen/agentchat/contrib/capabilities/agent_capability.py
autogen/agentchat/contrib/capabilities/generate_images.py
seed_pyautogen-0.5.0.dist-info/LICENSE
seed_pyautogen-0.5.0.dist-info/METADATA
seed_pyautogen-0.5.0.dist-info/NOTICE.md
seed_pyautogen-0.5.0.dist-info/WHEEL
seed_pyautogen-0.5.0.dist-info/top_level.txt
seed_pyautogen-0.5.0.dist-info/RECORD
