Metadata-Version: 2.2
Name: seed-pyautogen
Version: 0.5.0
Summary: A programming framework for agentic AI
Home-page: https://github.com/ag2ai/ag2
Author: Chi Wang & Qingyun Wu
Author-email: support@ag2.ai
License: Apache Software License 2.0
Classifier: Programming Language :: Python :: 3
Classifier: License :: OSI Approved :: Apache Software License
Classifier: Operating System :: OS Independent
Requires-Python: >=3.8,<3.14
License-File: LICENSE
License-File: NOTICE.md
Requires-Dist: openai>=1.3
Requires-Dist: diskcache
Requires-Dist: termcolor
Requires-Dist: flaml
Requires-Dist: numpy>=2.1; python_version >= "3.13"
Requires-Dist: numpy<2.0.0,>=1.24.0; python_version < "3.13"
Requires-Dist: python-dotenv
Requires-Dist: tiktoken
Requires-Dist: pydantic!=2.6.0,<3,>=1.10
Requires-Dist: docker
Requires-Dist: packaging
Provides-Extra: test
Requires-Dist: ipykernel; extra == "test"
Requires-Dist: nbconvert; extra == "test"
Requires-Dist: nbformat; extra == "test"
Requires-Dist: pre-commit; extra == "test"
Requires-Dist: pytest-cov>=5; extra == "test"
Requires-Dist: pytest-asyncio; extra == "test"
Requires-Dist: pytest<8,>=6.1.1; extra == "test"
Requires-Dist: pandas; extra == "test"
Provides-Extra: blendsearch
Requires-Dist: flaml[blendsearch]; extra == "blendsearch"
Provides-Extra: mathchat
Requires-Dist: sympy; extra == "mathchat"
Requires-Dist: pydantic==1.10.9; extra == "mathchat"
Requires-Dist: wolframalpha; extra == "mathchat"
Provides-Extra: retrievechat
Requires-Dist: protobuf==4.25.3; extra == "retrievechat"
Requires-Dist: chromadb==0.5.3; extra == "retrievechat"
Requires-Dist: sentence_transformers; extra == "retrievechat"
Requires-Dist: pypdf; extra == "retrievechat"
Requires-Dist: ipython; extra == "retrievechat"
Requires-Dist: beautifulsoup4; extra == "retrievechat"
Requires-Dist: markdownify; extra == "retrievechat"
Provides-Extra: retrievechat-pgvector
Requires-Dist: protobuf==4.25.3; extra == "retrievechat-pgvector"
Requires-Dist: chromadb==0.5.3; extra == "retrievechat-pgvector"
Requires-Dist: sentence_transformers; extra == "retrievechat-pgvector"
Requires-Dist: pypdf; extra == "retrievechat-pgvector"
Requires-Dist: ipython; extra == "retrievechat-pgvector"
Requires-Dist: beautifulsoup4; extra == "retrievechat-pgvector"
Requires-Dist: markdownify; extra == "retrievechat-pgvector"
Requires-Dist: pgvector>=0.2.5; extra == "retrievechat-pgvector"
Requires-Dist: psycopg[binary]>=3.1.18; extra == "retrievechat-pgvector"
Provides-Extra: retrievechat-mongodb
Requires-Dist: protobuf==4.25.3; extra == "retrievechat-mongodb"
Requires-Dist: chromadb==0.5.3; extra == "retrievechat-mongodb"
Requires-Dist: sentence_transformers; extra == "retrievechat-mongodb"
Requires-Dist: pypdf; extra == "retrievechat-mongodb"
Requires-Dist: ipython; extra == "retrievechat-mongodb"
Requires-Dist: beautifulsoup4; extra == "retrievechat-mongodb"
Requires-Dist: markdownify; extra == "retrievechat-mongodb"
Requires-Dist: pymongo>=4.0.0; extra == "retrievechat-mongodb"
Provides-Extra: retrievechat-qdrant
Requires-Dist: protobuf==4.25.3; extra == "retrievechat-qdrant"
Requires-Dist: chromadb==0.5.3; extra == "retrievechat-qdrant"
Requires-Dist: sentence_transformers; extra == "retrievechat-qdrant"
Requires-Dist: pypdf; extra == "retrievechat-qdrant"
Requires-Dist: ipython; extra == "retrievechat-qdrant"
Requires-Dist: beautifulsoup4; extra == "retrievechat-qdrant"
Requires-Dist: markdownify; extra == "retrievechat-qdrant"
Requires-Dist: qdrant_client; extra == "retrievechat-qdrant"
Requires-Dist: fastembed>=0.3.1; extra == "retrievechat-qdrant"
Provides-Extra: graph-rag-falkor-db
Requires-Dist: graphrag_sdk==0.3.3; extra == "graph-rag-falkor-db"
Requires-Dist: falkordb>=1.0.10; extra == "graph-rag-falkor-db"
Provides-Extra: autobuild
Requires-Dist: chromadb; extra == "autobuild"
Requires-Dist: sentence-transformers; extra == "autobuild"
Requires-Dist: huggingface-hub; extra == "autobuild"
Requires-Dist: pysqlite3-binary; extra == "autobuild"
Provides-Extra: captainagent
Requires-Dist: chromadb; extra == "captainagent"
Requires-Dist: sentence-transformers; extra == "captainagent"
Requires-Dist: huggingface-hub; extra == "captainagent"
Requires-Dist: pysqlite3-binary; extra == "captainagent"
Requires-Dist: pandas; extra == "captainagent"
Provides-Extra: teachable
Requires-Dist: chromadb; extra == "teachable"
Provides-Extra: lmm
Requires-Dist: replicate; extra == "lmm"
Requires-Dist: pillow; extra == "lmm"
Provides-Extra: graph
Requires-Dist: networkx; extra == "graph"
Requires-Dist: matplotlib; extra == "graph"
Provides-Extra: gemini
Requires-Dist: google-generativeai<1,>=0.5; extra == "gemini"
Requires-Dist: google-cloud-aiplatform; extra == "gemini"
Requires-Dist: google-auth; extra == "gemini"
Requires-Dist: pillow; extra == "gemini"
Requires-Dist: pydantic; extra == "gemini"
Provides-Extra: together
Requires-Dist: together>=1.2; extra == "together"
Provides-Extra: websurfer
Requires-Dist: beautifulsoup4; extra == "websurfer"
Requires-Dist: markdownify; extra == "websurfer"
Requires-Dist: pdfminer.six; extra == "websurfer"
Requires-Dist: pathvalidate; extra == "websurfer"
Provides-Extra: redis
Requires-Dist: redis; extra == "redis"
Provides-Extra: cosmosdb
Requires-Dist: azure-cosmos>=4.2.0; extra == "cosmosdb"
Provides-Extra: websockets
Requires-Dist: websockets<13,>=12.0; extra == "websockets"
Provides-Extra: jupyter-executor
Requires-Dist: jupyter-kernel-gateway; extra == "jupyter-executor"
Requires-Dist: websocket-client; extra == "jupyter-executor"
Requires-Dist: requests; extra == "jupyter-executor"
Requires-Dist: jupyter-client>=8.6.0; extra == "jupyter-executor"
Requires-Dist: ipykernel>=6.29.0; extra == "jupyter-executor"
Provides-Extra: types
Requires-Dist: mypy==1.9.0; extra == "types"
Requires-Dist: pytest<8,>=6.1.1; extra == "types"
Requires-Dist: jupyter-kernel-gateway; extra == "types"
Requires-Dist: websocket-client; extra == "types"
Requires-Dist: requests; extra == "types"
Requires-Dist: jupyter-client>=8.6.0; extra == "types"
Requires-Dist: ipykernel>=6.29.0; extra == "types"
Provides-Extra: long-context
Requires-Dist: llmlingua<0.3; extra == "long-context"
Provides-Extra: anthropic
Requires-Dist: anthropic>=0.23.1; extra == "anthropic"
Provides-Extra: cerebras
Requires-Dist: cerebras_cloud_sdk>=1.0.0; extra == "cerebras"
Provides-Extra: mistral
Requires-Dist: mistralai>=1.0.1; extra == "mistral"
Provides-Extra: groq
Requires-Dist: groq>=0.9.0; extra == "groq"
Provides-Extra: cohere
Requires-Dist: cohere>=5.5.8; extra == "cohere"
Provides-Extra: ollama
Requires-Dist: ollama>=0.3.3; extra == "ollama"
Requires-Dist: fix_busted_json>=0.0.18; extra == "ollama"
Provides-Extra: bedrock
Requires-Dist: boto3>=1.34.149; extra == "bedrock"
Dynamic: author
Dynamic: author-email
Dynamic: classifier
Dynamic: description
Dynamic: description-content-type
Dynamic: home-page
Dynamic: license
Dynamic: provides-extra
Dynamic: requires-dist
Dynamic: requires-python
Dynamic: summary
